{
  "$schema": "https://turbo.build/schema.json",
  "ui": "tui",
  "globalPassThroughEnv": ["CARGO_HOME", "RUSTUP_HOME"],
  "tasks": {
    "build": {
      "dependsOn": ["^build"],
      "inputs": ["$TURBO_DEFAULT$", ".env*"],
      "outputs": [".output/**", "target/**"]
    },
    "codegen": {
      "cache": false
    },
    "lint": {
      "dependsOn": ["^lint"]
    },
    "format": {
      "dependsOn": ["^format"]
    },
    "typecheck": {
      "dependsOn": ["^typecheck"]
    },
    "dev": {
      "cache": false,
      "persistent": true
    }
  }
}
